buildbot_www_react/VERSION
buildbot_www_react/__init__.py
buildbot_www_react/static/browser-warning-list.js
buildbot_www_react/static/browser-warning.css
buildbot_www_react/static/browser-warning.js
buildbot_www_react/static/icon.png
buildbot_www_react/static/icon.svg
buildbot_www_react/static/index.html
buildbot_www_react/static/manifest.json
buildbot_www_react/static/robots.txt
buildbot_www_react/static/assets/index-D5n2Y-ls.css
buildbot_www_react/static/assets/index-D6XzErTH.js
buildbot_www_react-4.0.4.dist-info/METADATA
buildbot_www_react-4.0.4.dist-info/WHEEL
buildbot_www_react-4.0.4.dist-info/entry_points.txt
buildbot_www_react-4.0.4.dist-info/top_level.txt
buildbot_www_react-4.0.4.dist-info/RECORD
