Metadata-Version: 2.1
Name: buildbot-www-react
Version: 4.0.4
Summary: Buildbot UI (React)
Home-page: http://buildbot.net/
Author: Povilas Kanapickas
Author-email: povilas@radix.lt
Classifier: License :: OSI Approved :: GNU General Public License v2 (GPLv2)
Requires-Dist: buildbot
